MANIFEST.in
README.txt
setup.cfg
setup.py
docs/HISTORY.txt
docs/LICENSE.txt
raptus/__init__.py
raptus.multilanguagefields.egg-info/PKG-INFO
raptus.multilanguagefields.egg-info/SOURCES.txt
raptus.multilanguagefields.egg-info/dependency_links.txt
raptus.multilanguagefields.egg-info/entry_points.txt
raptus.multilanguagefields.egg-info/namespace_packages.txt
raptus.multilanguagefields.egg-info/not-zip-safe
raptus.multilanguagefields.egg-info/requires.txt
raptus.multilanguagefields.egg-info/top_level.txt
raptus/multilanguagefields/README.txt
raptus/multilanguagefields/__init__.py
raptus/multilanguagefields/browser.py
raptus/multilanguagefields/config.py
raptus/multilanguagefields/configure.zcml
raptus/multilanguagefields/criteria.py
raptus/multilanguagefields/fields.py
raptus/multilanguagefields/interfaces.py
raptus/multilanguagefields/permissions.py
raptus/multilanguagefields/widgets.py
raptus/multilanguagefields/Extensions/Install.py
raptus/multilanguagefields/Extensions/__init__.py
raptus/multilanguagefields/i18n/raptus.multilanguagefields-de.mo
raptus/multilanguagefields/i18n/raptus.multilanguagefields-de.po
raptus/multilanguagefields/i18n/raptus.multilanguagefields-fr.mo
raptus/multilanguagefields/i18n/raptus.multilanguagefields-fr.po
raptus/multilanguagefields/indexes/DateIndex.py
raptus/multilanguagefields/indexes/DateRangeIndex.py
raptus/multilanguagefields/indexes/FieldIndex.py
raptus/multilanguagefields/indexes/KeywordIndex.py
raptus/multilanguagefields/indexes/UnIndex.py
raptus/multilanguagefields/indexes/ZCTextIndex.py
raptus/multilanguagefields/indexes/__init__.py
raptus/multilanguagefields/indexes/configure.zcml
raptus/multilanguagefields/indexes/dtml/addDateIndex.dtml
raptus/multilanguagefields/indexes/dtml/addDateRangeIndex.dtml
raptus/multilanguagefields/indexes/dtml/addFieldIndex.dtml
raptus/multilanguagefields/indexes/dtml/addKeywordIndex.dtml
raptus/multilanguagefields/indexes/dtml/addZCTextIndex.dtml
raptus/multilanguagefields/kss/__init__.py
raptus/multilanguagefields/kss/configure.zcml
raptus/multilanguagefields/kss/multilanguagefields.kss
raptus/multilanguagefields/kss/plugins.js
raptus/multilanguagefields/kss/validation.py
raptus/multilanguagefields/locales/raptus.multilanguagefields.pot
raptus/multilanguagefields/locales/update.sh
raptus/multilanguagefields/locales/de/LC_MESSAGES/raptus.multilanguagefields.mo
