Metadata-Version: 1.0
Name: raptus.multilanguagefields
Version: 1.0
Summary: Providing multi language fields and widgets
Home-page: http://plone.org/products/raptus.multilanguagefields
Author: Raptus AG
Author-email: dev@raptus.com
License: GPL
Keywords: plone archetypes widgets fields
Platform: UNKNOWN
Classifier: Programming Language :: Python
Classifier: Topic :: Software Development :: Libraries :: Python Modules
Classifier: License :: OSI Approved :: GNU General Public License (GPL)
